atlasai/mlhub/client/__init__.py
atlasai/mlhub/client/authenticate.py
atlasai/mlhub/client/constants.py
atlasai/mlhub/client/discovery.py
atlasai/mlhub/client/evaluate.py
atlasai/mlhub/client/job.py
atlasai/mlhub/client/model.py
atlasai/mlhub/client/output.py
atlasai/mlhub/client/requests.py
atlasai/mlhub/client/response.py
atlasai/mlhub/client/utils.py
atlasai_mlhub_client-0.0.9.dist-info/LICENSE.txt
atlasai_mlhub_client-0.0.9.dist-info/METADATA
atlasai_mlhub_client-0.0.9.dist-info/WHEEL
atlasai_mlhub_client-0.0.9.dist-info/top_level.txt
atlasai_mlhub_client-0.0.9.dist-info/RECORD
