Metadata-Version: 2.1
Name: atlasai-mlhub-client
Version: 0.0.9
Summary: UNKNOWN
Home-page: UNKNOWN
Author: AtlasAI SWE
Author-email: software-engineers@atlasai.us
License: UNKNOWN
Platform: UNKNOWN
Requires-Python: >=3.8
License-File: LICENSE.txt
Requires-Dist: arrow>=1.3.0
Requires-Dist: furl>=2.1.3
Requires-Dist: requests>=2.31.0
Requires-Dist: rich~=13.9.4
Provides-Extra: dev
Requires-Dist: coverage; extra == "dev"
Requires-Dist: flake8; extra == "dev"
Requires-Dist: ipdb; extra == "dev"
Requires-Dist: ipython; extra == "dev"
Requires-Dist: keyrings.google-artifactregistry-auth; extra == "dev"
Requires-Dist: line-profiler; extra == "dev"
Requires-Dist: memory-profiler; extra == "dev"
Requires-Dist: mock; extra == "dev"
Requires-Dist: pycallgraph2; extra == "dev"
Requires-Dist: pytest; extra == "dev"
Requires-Dist: pytest-cov; extra == "dev"
Requires-Dist: requests-mock; extra == "dev"
Requires-Dist: twine; extra == "dev"
Provides-Extra: dist
Requires-Dist: keyrings.google-artifactregistry-auth; extra == "dist"
Requires-Dist: twine; extra == "dist"
Provides-Extra: test
Requires-Dist: coverage; extra == "test"
Requires-Dist: mock; extra == "test"
Requires-Dist: pytest; extra == "test"
Requires-Dist: pytest-cov; extra == "test"
Requires-Dist: requests-mock; extra == "test"
